LICENSE
README.md
pyproject.toml
setup.cfg
setup.py
anomaly_impact_alert/__init__.py
anomaly_impact_alert/alert_bot.py
anomaly_impact_alert/alert_bot_telegram.py
anomaly_impact_alert/anomaly_detector.py
anomaly_impact_alert/forecast.py
anomaly_impact_alert/impact_explainer.py
anomaly_impact_alert.egg-info/PKG-INFO
anomaly_impact_alert.egg-info/SOURCES.txt
anomaly_impact_alert.egg-info/dependency_links.txt
anomaly_impact_alert.egg-info/requires.txt
anomaly_impact_alert.egg-info/top_level.txt
docs/example_detection.png
docs/example_telegram.png