Metadata-Version: 2.4
Name: anomaly_impact_alert
Version: 0.4.8
Summary: Anomaly detection, impact explanation, forecasting, and alerting toolkit
Author: Alexey Voronko
License: MIT
Requires-Python: >=3.9
License-File: LICENSE
Requires-Dist: pandas>=1.3
Requires-Dist: numpy>=1.21
Requires-Dist: scikit-learn>=1.0
Requires-Dist: matplotlib>=3.5
Requires-Dist: prophet>=1.1
Requires-Dist: tqdm>=4.0
Requires-Dist: requests>=2.0
Requires-Dist: python-telegram-bot>=20.0
Dynamic: license-file
Dynamic: requires-python
